quark/__init__.py
quarkstudio-7.2.2.dist-info/licenses/LICENSE
quarkstudio-7.2.2.dist-info/METADATA
quarkstudio-7.2.2.dist-info/WHEEL
quarkstudio-7.2.2.dist-info/top_level.txt
quarkstudio-7.2.2.dist-info/RECORD
