Metadata-Version: 2.4
Name: quarkstudio
Version: 7.2.2
Summary: quantum computing
Author-email: YL Feng <fengyl@baqis.ac.cn>
License-Expression: MIT
Project-URL: homepage, https://quarkstudio.readthedocs.io/en/latest
Classifier: Development Status :: 5 - Production/Stable
Classifier: Intended Audience :: Developers
Classifier: Intended Audience :: Science/Research
Classifier: Natural Language :: Chinese (Simplified)
Classifier: Natural Language :: English
Classifier: Operating System :: Microsoft :: Windows
Classifier: Operating System :: POSIX :: Linux
Classifier: Operating System :: MacOS :: MacOS X
Classifier: Programming Language :: Python :: 3.12
Classifier: Topic :: Scientific/Engineering :: Physics
Requires-Python: >=3.12
License-File: LICENSE
Requires-Dist: clirk>=1.2.0
Requires-Dist: requests
Requires-Dist: srpc
Provides-Extra: remote
Requires-Dist: clirk[remote]>=1.2.0; extra == "remote"
Provides-Extra: server
Requires-Dist: clirk[server]>=1.2.0; extra == "server"
Provides-Extra: studio
Requires-Dist: clirk[studio]>=1.2.0; extra == "studio"
Provides-Extra: full
Requires-Dist: clirk[full]>=1.2.0; extra == "full"
Dynamic: license-file
